{
  "type": "bubble",
  "styles": {
    "footer": {
      "separator": true
    }
  },
  "body": {
    "type": "box",
    "layout": "vertical",
    "contents": [
      {
        "type": "text",
        "text": "資料確認",
        "weight": "bold",
        "color": "#1DB446",
        "size": "xxl",
        "margin": "md"
      },
      {
        "type": "separator",
        "margin": "xxl"
      },
      {
        "type": "box",
        "layout": "vertical",
        "margin": "xxl",
        "spacing": "sm",
        "contents": [
          {
            "type": "box",
            "layout": "horizontal",
            "contents": [
              {
                "type": "text",
                "text": "姓名",
                "size": "sm",
                "color": "#555555",
                "flex": 0
              },
              {
                "type": "text",
                "text": "Jason",
                "size": "sm",
                "color": "#111111",
                "align": "end"
              }
            ]
          },
          {
            "type": "box",
            "layout": "horizontal",
            "contents": [
              {
                "type": "text",
                "text": "電話",
                "size": "sm",
                "color": "#555555",
                "flex": 0
              },
              {
                "type": "text",
                "text": "0918123123",
                "size": "sm",
                "color": "#111111",
                "align": "end"
              }
            ]
          },
          {
            "type": "box",
            "layout": "horizontal",
            "contents": [
              {
                "type": "text",
                "text": "生日",
                "size": "sm",
                "color": "#555555",
                "flex": 0
              },
              {
                "type": "text",
                "text": "85/01/01",
                "size": "sm",
                "color": "#111111",
                "align": "end"
              }
            ]
          }
        ]
      },
      {
        "type": "separator",
        "margin": "xxl"
      }
    ]
  }
}